pylint_reenable.py
pylint_reenable-0.1.4.dist-info/LICENSE
pylint_reenable-0.1.4.dist-info/METADATA
pylint_reenable-0.1.4.dist-info/WHEEL
pylint_reenable-0.1.4.dist-info/entry_points.txt
pylint_reenable-0.1.4.dist-info/top_level.txt
pylint_reenable-0.1.4.dist-info/RECORD
