Metadata-Version: 2.1
Name: pylint-reenable
Version: 0.1.4
Summary: Automatically remove unnecessary `# pylint-disable` comments.
Home-page: https://github.com/MarcoGorelli/pylint-reenable
Author: Marco Gorelli
License: MIT
Classifier: License :: OSI Approved :: MIT License
Classifier: Programming Language :: Python :: 3
Classifier: Programming Language :: Python :: 3 :: Only
Classifier: Programming Language :: Python :: Implementation :: CPython
Classifier: Programming Language :: Python :: Implementation :: PyPy
Requires-Python: >=3.7
License-File: LICENSE
Requires-Dist: pylint (>=2.9.0)
Requires-Dist: tokenize-rt (>=2.1)
